data_dispatcher/__init__.py
data_dispatcher/api.py
data_dispatcher/db.py
data_dispatcher/timelib.py
data_dispatcher/version.py
data_dispatcher/ddsam/ddsam.py
data_dispatcher/logs/__init__.py
data_dispatcher/logs/log_file.py
data_dispatcher/logs/logs.py
data_dispatcher/query/__init__.py
data_dispatcher/query/grammar.py
data_dispatcher/query/query.py
data_dispatcher/query/trees.py
data_dispatcher/ui/json_extract.py
data_dispatcher/ui/ui_file.py
data_dispatcher/ui/ui_lib.py
data_dispatcher/ui/ui_main.py
data_dispatcher/ui/ui_project.py
data_dispatcher/ui/ui_rse.py
data_dispatcher/ui/ui_worker.py
data_dispatcher/ui/cli/__init__.py
data_dispatcher/ui/cli/cli.py
data_dispatcher/ui/cli/tabular.py
datadispatcher-1.27.0.dist-info/LICENSE
datadispatcher-1.27.0.dist-info/METADATA
datadispatcher-1.27.0.dist-info/WHEEL
datadispatcher-1.27.0.dist-info/entry_points.txt
datadispatcher-1.27.0.dist-info/top_level.txt
datadispatcher-1.27.0.dist-info/RECORD
