Metadata-Version: 2.1
Name: datadispatcher
Version: 1.27.0
Summary: Data Dispatcher - core workflow management
Home-page: https://github.com/ivmfnal/data_dispatcher
Author: Igor Mandrichenko
Author-email: ivm@fnal.gov
License: BSD 3-clause
Keywords: workflow management,data management,web service
License-File: LICENSE
Requires-Dist: metacat (>=3.26.0)
Requires-Dist: requests
